gera2ld/aioproxy/__init__.py
gera2ld/aioproxy/cli.py
gera2ld/aioproxy/handlers/__init__.py
gera2ld/aioproxy/handlers/http.py
gera2ld/aioproxy/handlers/socks.py
gera2ld.aioproxy-0.4.1.dist-info/entry_points.txt
gera2ld.aioproxy-0.4.1.dist-info/WHEEL
gera2ld.aioproxy-0.4.1.dist-info/METADATA
gera2ld.aioproxy-0.4.1.dist-info/RECORD
