Metadata-Version: 2.1
Name: gera2ld.aioproxy
Version: 0.4.1
Summary: 
Home-page: https://github.com/gera2ld/aioproxy
License: MIT
Author: Gerald
Author-email: gera2ld@163.com
Requires-Python: >=3.7,<4.0
Classifier: License :: OSI Approved :: MIT License
Classifier: Programming Language :: Python :: 3
Classifier: Programming Language :: Python :: 3.7
Classifier: Programming Language :: Python :: 3.8
Classifier: Programming Language :: Python :: 3.9
Requires-Dist: click (>=7.0,<8.0)
Requires-Dist: gera2ld.socks (>=0.5.0,<0.6.0)
Requires-Dist: importlib_metadata (>=1.7.0,<2.0.0)
Project-URL: Repository, https://github.com/gera2ld/aioproxy
